synchrotron/__init__.py
synchrotron/synchrotron.py
synchrotron/console/__init__.py
synchrotron/console/__main__.py
synchrotron/console/app.py
synchrotron/console/app.tcss
synchrotron/nodes/__init__.py
synchrotron/nodes/_base.py
synchrotron/nodes/_midi.py
synchrotron/nodes/audio.py
synchrotron/nodes/core.py
synchrotron/nodes/data.py
synchrotron/nodes/midi.py
synchrotron/nodes/tone.py
synchrotron/nodes/soundfonts/8MBGMSFX.sf2
synchrotron/nodes/soundfonts/SM64.sf2
synchrotron/server/__init__.py
synchrotron/server/__main__.py
synchrotron/server/api.py
synchrotron/server/cli.py
synchrotron/server/dependencies.py
synchrotron/server/models.py
synchrotron/server/server.py
synchrotron/synchrolang/__init__.py
synchrotron/synchrolang/parser.py
synchrotron/synchrolang/synchrolang.lark
synchrotron/synchrolang/transformer.py
synchrotron-0.1.0.dist-info/METADATA
synchrotron-0.1.0.dist-info/WHEEL
synchrotron-0.1.0.dist-info/entry_points.txt
synchrotron-0.1.0.dist-info/licenses/LICENSE
synchrotron-0.1.0.dist-info/RECORD
