Metadata-Version: 2.4
Name: synchrotron
Version: 0.1.0
Summary: Graph-based live audio manipulation engine implemented in Python
Project-URL: Homepage, https://synchrotron.thatother.dev
Project-URL: Bug Reports, https://github.com/ThatOtherAndrew/Synchrotron/issues
Project-URL: Source, https://github.com/ThatOtherAndrew/Synchrotron
Author-email: ThatOtherAndrew <andrew@thatother.dev>
Maintainer-email: ThatOtherAndrew <andrew@thatother.dev>
License-Expression: LGPL-3.0-only
License-File: LICENSE
Keywords: audio-processing,dsp,live-coding,synthesiser,synthesizer
Classifier: Development Status :: 3 - Alpha
Classifier: Environment :: Console
Classifier: Environment :: Web Environment
Classifier: Intended Audience :: Developers
Classifier: Intended Audience :: Education
Classifier: Intended Audience :: End Users/Desktop
Classifier: Operating System :: OS Independent
Classifier: Programming Language :: Python :: 3
Classifier: Programming Language :: Python :: 3 :: Only
Classifier: Programming Language :: Python :: 3.11
Classifier: Programming Language :: Python :: 3.12
Classifier: Topic :: Artistic Software
Classifier: Topic :: Multimedia :: Sound/Audio
Classifier: Topic :: Multimedia :: Sound/Audio :: Mixers
Classifier: Topic :: Multimedia :: Sound/Audio :: Players
Classifier: Topic :: Multimedia :: Sound/Audio :: Sound Synthesis
Classifier: Topic :: Software Development :: Build Tools
Requires-Python: >=3.11
Requires-Dist: aiohttp>=3.12.13
Requires-Dist: fastapi>=0.115.13
Requires-Dist: lark>=1.2.2
Requires-Dist: mingus>=0.6.1
Requires-Dist: numpy>=2.3.1
Requires-Dist: pyaudio>=0.2.14
Requires-Dist: python-rtmidi>=1.5.8
Requires-Dist: soundfile>=0.13.1
Requires-Dist: textual>=3.5.0
Requires-Dist: tinysoundfont>=0.3.7
Requires-Dist: typer>=0.16.0
Requires-Dist: uvicorn>=0.34.3
